random_quote/__init__.py
random_quote/main.py
random_quote_malam-1.1.1.dist-info/METADATA
random_quote_malam-1.1.1.dist-info/WHEEL
random_quote_malam-1.1.1.dist-info/entry_points.txt
random_quote_malam-1.1.1.dist-info/RECORD
