Metadata-Version: 2.1
Name: random-quote-malam
Version: 1.1.1
Summary: 
Author: mahfooz.iiitian
Author-email: mahfooz.iiitian@gmail.com
Requires-Python: >=3.11,<4.0
Classifier: Programming Language :: Python :: 3
Classifier: Programming Language :: Python :: 3.11
Classifier: Programming Language :: Python :: 3.12
Requires-Dist: requests (>=2.32.3,<3.0.0)
